Python_CAN_Viewer-0.2.0.dist-info/METADATA
Python_CAN_Viewer-0.2.0.dist-info/RECORD
Python_CAN_Viewer-0.2.0.dist-info/WHEEL
Python_CAN_Viewer-0.2.0.dist-info/top_level.txt
python_can_viewer/__init__.py
python_can_viewer/__main__.py
python_can_viewer/python_can_viewer.py
