Metadata-Version: 2.1
Name: Python-CAN-Viewer
Version: 0.2.0
Summary: A simple CAN viewer terminal application written in Python
Home-page: https://github.com/Lauszus/python_can_viewer
Author: Kristian Sloth Lauszus
Author-email: lauszus@gmail.com
License: GPLv2
Platform: UNKNOWN
Classifier: Programming Language :: Python :: 2
Classifier: Programming Language :: Python :: 3
Classifier: License :: OSI Approved :: GNU General Public License v2 (GPLv2)
Classifier: Operating System :: OS Independent
Requires-Python: >=2.7
Provides-Extra: test
Requires-Dist: python-can (>=2.0.0)
Requires-Dist: six
Requires-Dist: typing
Requires-Dist: windows-curses; platform_system == "Windows"
Provides-Extra: test
Requires-Dist: future; extra == 'test'
Requires-Dist: mock; extra == 'test'
Requires-Dist: pytest; extra == 'test'
Requires-Dist: pytest-runner; extra == 'test'
Requires-Dist: coverage; extra == 'test'
Requires-Dist: codecov; extra == 'test'
